fastcda/__init__.py
fastcda/fastcda.py
fastcda/data/R34B01.csv
fastcda/data/R34B08.csv
fastcda/data/R34B13.csv
fastcda/data/R34B23.csv
fastcda/data/boston_data_raw.csv
fastcda/data/boston_prior.txt
fastcda/data/fmri_48451_ptseries.csv
fastcda/jars/tetrad-gui-7.6.3-launch.jar
fastcda-0.1.18.dist-info/METADATA
fastcda-0.1.18.dist-info/WHEEL
fastcda-0.1.18.dist-info/top_level.txt
fastcda-0.1.18.dist-info/RECORD
