Metadata-Version: 2.4
Name: fastcda
Version: 0.1.18
Summary: A package of tools for working with the tetrad java program for causal discovery from CMU
Author-email: "Kelvin O. Lim" <lim.kelvino@gmail.com>
Project-URL: Homepage, https://github.com/kelvinlim/fastcda
Project-URL: Bug Tracker, https://github.com/kelvinlim/fastcda/issues
Classifier: Programming Language :: Python :: 3
Classifier: License :: OSI Approved :: MIT License
Classifier: Operating System :: OS Independent
Requires-Python: >=3.11
Requires-Dist: JPype1
Requires-Dist: pandas
Requires-Dist: python-dotenv
Requires-Dist: PyYAML
Requires-Dist: seaborn
Requires-Dist: semopy
Requires-Dist: graphviz
Requires-Dist: tqdm
Requires-Dist: ipykernel
Requires-Dist: dgraph_flex
Requires-Dist: ipywidgets
Requires-Dist: scikit-learn
Requires-Dist: ipython
Requires-Dist: ipykernel
Requires-Dist: matplotlib
